snt_malaria_budgeting/__init__.py
snt_malaria_budgeting/models.py
snt_malaria_budgeting/core/PATH_generate_budget.py
snt_malaria_budgeting/core/__init__.py
snt_malaria_budgeting/core/budget_calculator.py
snt_malaria_budgeting-0.5.1.dist-info/licenses/LICENSE.md
snt_malaria_budgeting-0.5.1.dist-info/METADATA
snt_malaria_budgeting-0.5.1.dist-info/WHEEL
snt_malaria_budgeting-0.5.1.dist-info/top_level.txt
snt_malaria_budgeting-0.5.1.dist-info/RECORD
