Metadata-Version: 2.4
Name: snt-malaria-budgeting
Version: 0.5.1
Summary: A Python library for calculating malaria intervention budgets
Author: PATH, IDM, Bluesquare
License: GPL-3.0-or-later
Project-URL: Homepage, https://github.com/BLSQ/snt-malaria-budgeting
Project-URL: Repository, https://github.com/BLSQ/snt-malaria-budgeting
Classifier: Development Status :: 3 - Alpha
Classifier: Intended Audience :: Healthcare Industry
Classifier: Intended Audience :: Science/Research
Classifier: License :: OSI Approved :: GNU General Public License v3 or later (GPLv3+)
Classifier: Operating System :: OS Independent
Classifier: Programming Language :: Python :: 3
Classifier: Programming Language :: Python :: 3.9
Classifier: Programming Language :: Python :: 3.10
Classifier: Programming Language :: Python :: 3.11
Classifier: Programming Language :: Python :: 3.12
Classifier: Programming Language :: Python :: 3.13
Classifier: Topic :: Scientific/Engineering
Classifier: Topic :: Software Development :: Libraries :: Python Modules
Requires-Python: >=3.9
License-File: LICENSE.md
Requires-Dist: pandas
Requires-Dist: numpy
Requires-Dist: openpyxl
Requires-Dist: pydantic
Requires-Dist: python-dotenv
Requires-Dist: cachetools
Requires-Dist: requests
Provides-Extra: dev
Requires-Dist: build<2,>=1.3; extra == "dev"
Requires-Dist: pytest>=6.0; extra == "dev"
Requires-Dist: pytest-cov>=2.0; extra == "dev"
Requires-Dist: ruff==0.14.10; extra == "dev"
Requires-Dist: mypy>=0.812; extra == "dev"
Requires-Dist: pandas-stubs; extra == "dev"
Provides-Extra: test
Requires-Dist: pytest>=6.0; extra == "test"
Requires-Dist: pytest-cov>=2.0; extra == "test"
Dynamic: license-file
